pyEntrez/__init__.py
pyEntrez/__main__.py
pyEntrez/cmdline.py
pyEntrez/commands.py
pyEntrez/config/default_config.yaml
pyEntrez/entrez/__init__.py
pyEntrez/entrez/entrez_scraper.py
pyEntrez/fetch_screen.py
pyEntrez/pyEntrezManager.py
pyEntrez/screen_manager.py
pyEntrez/settings_screen.py
pyEntrez/utils/__init__.py
pyEntrez/utils/logger_utils.py
pyEntrez/utils/string_utils.py
README.rst
pyentrez-0.1.0.dist-info/entry_points.txt
pyentrez-0.1.0.dist-info/LICENSE
pyentrez-0.1.0.dist-info/WHEEL
pyentrez-0.1.0.dist-info/METADATA
pyentrez-0.1.0.dist-info/RECORD
