Metadata-Version: 2.1
Name: pyentrez
Version: 0.1.0
Summary: pyEntrez tool suite wrapped in pyCUI TUI
Home-page: https://github.com/BGASM/pyEntrez
License: MIT
Author: William Slattery
Author-email: slatte26@msu.edu
Requires-Python: >=3.8,<4.0
Classifier: License :: OSI Approved :: MIT License
Classifier: Programming Language :: Python :: 3
Classifier: Programming Language :: Python :: 3.8
Classifier: Programming Language :: Python :: 3.9
Requires-Dist: ConfigArgParse (>=1.2.3,<2.0.0)
Requires-Dist: PyYAML (>=5.3.1,<6.0.0)
Requires-Dist: biopython (>=1.78,<2.0)
Requires-Dist: keyring (>=21.5.0,<22.0.0)
Requires-Dist: loguru (>=0.5.3,<0.6.0)
Requires-Dist: py-cui (>=0.1.2,<0.2.0)
Project-URL: Documentation, https://pyentrez.readthedocs.io/en/latest/
Project-URL: Repository, https://github.com/BGASM/pyEntrez
